LICENSE.txt
MANIFEST.in
README.rst
TODO.txt
setup.py
whooshalchemy.py
WhooshAlchemy3.egg-info/PKG-INFO
WhooshAlchemy3.egg-info/SOURCES.txt
WhooshAlchemy3.egg-info/dependency_links.txt
WhooshAlchemy3.egg-info/not-zip-safe
WhooshAlchemy3.egg-info/requires.txt
WhooshAlchemy3.egg-info/top_level.txt