Metadata-Version: 1.1
Name: WhooshAlchemy3
Version: 0.1.5
Summary: Whoosh extension to SQLAlchemy
Home-page: https://github.com/nicholasday/WhooshAlchemy
Author: Nicholas Day
Author-email: nick@nickendo.com
License: BSD
Platform: any
Classifier: Intended Audience :: Developers
Classifier: License :: OSI Approved :: BSD License
Classifier: Operating System :: OS Independent
Classifier: Programming Language :: Python
Classifier: Topic :: Software Development :: Libraries :: Python Modules
